LICENSE
README.md
setup.py
openai_playground/__init__.py
openai_playground/append.js
openai_playground/full.js
openai_playground/logger.py
openai_playground/main.py
openai_playground/utils.py
openai_playground.egg-info/PKG-INFO
openai_playground.egg-info/SOURCES.txt
openai_playground.egg-info/dependency_links.txt
openai_playground.egg-info/requires.txt
openai_playground.egg-info/top_level.txt