Metadata-Version: 2.1
Name: openai-playground
Version: 1.1.2
Summary: Use other openai-compatible API services in OpenAI Playground.
Home-page: https://github.com/jtc1246/openai-playground
Author: Tiancheng Jiao
Author-email: jtc1246@outlook.com
License: GPL-2.0 License
Platform: all
Requires-Python: >=3.9
License-File: LICENSE
